syinfo/__init__.py
syinfo/__main__.py
syinfo/_version.py
syinfo/constants.py
syinfo/exceptions.py
syinfo/analysis/__init__.py
syinfo/analysis/logs.py
syinfo/analysis/packages.py
syinfo/builder/__init__.py
syinfo/builder/config.py
syinfo/builder/facade.py
syinfo/core/__init__.py
syinfo/core/device_info.py
syinfo/core/network_info.py
syinfo/core/search_network.py
syinfo/core/system_info.py
syinfo/resource_monitor/__init__.py
syinfo/resource_monitor/process_monitoring.py
syinfo/resource_monitor/system_monitor.py
syinfo/resource_monitor/visualization.py
syinfo/utils/__init__.py
syinfo/utils/common.py
syinfo/utils/export.py
syinfo/utils/formatters.py
syinfo/utils/logger.py
syinfo/utils/system.py
syinfo-0.3.0.dist-info/METADATA
syinfo-0.3.0.dist-info/WHEEL
syinfo-0.3.0.dist-info/entry_points.txt
syinfo-0.3.0.dist-info/licenses/LICENSE
syinfo-0.3.0.dist-info/RECORD
