Metadata-Version: 2.4
Name: syinfo
Version: 0.3.0
Summary: A comprehensive Python package for hardware, network, and software information gathering with advanced monitoring capabilities
Project-URL: Homepage, https://github.com/MR901/syinfo
Project-URL: Repository, https://github.com/MR901/syinfo
Project-URL: Documentation, https://syinfo.readthedocs.io
Project-URL: Changelog, https://github.com/MR901/syinfo/blob/main/CHANGELOG.md
Project-URL: Bug Tracker, https://github.com/MR901/syinfo/issues
Author-email: Mohit Rajput <mohitrajput901@gmail.com>
Maintainer-email: Mohit Rajput <mohitrajput901@gmail.com>
License: MIT
License-File: LICENSE
Keywords: analytics,devops,hardware,information,linux,monitoring,network,performance,system
Classifier: Development Status :: 4 - Beta
Classifier: Environment :: Console
Classifier: Intended Audience :: Developers
Classifier: Intended Audience :: Science/Research
Classifier: Intended Audience :: System Administrators
Classifier: License :: OSI Approved :: MIT License
Classifier: Operating System :: POSIX
Classifier: Operating System :: POSIX :: Linux
Classifier: Operating System :: Unix
Classifier: Programming Language :: Python
Classifier: Programming Language :: Python :: 3
Classifier: Programming Language :: Python :: 3.8
Classifier: Programming Language :: Python :: 3.9
Classifier: Programming Language :: Python :: 3.10
Classifier: Programming Language :: Python :: 3.11
Classifier: Programming Language :: Python :: 3.12
Classifier: Topic :: Scientific/Engineering
Classifier: Topic :: Software Development :: Libraries
Classifier: Topic :: System :: Monitoring
Classifier: Topic :: System :: Systems Administration
Classifier: Typing :: Typed
Requires-Python: >=3.8
Requires-Dist: getmac>=0.9.4
Requires-Dist: gputil>=1.4.0
Requires-Dist: matplotlib>=3.5.0
Requires-Dist: numpy>=1.21.0
Requires-Dist: pandas>=1.5.0
Requires-Dist: paramiko>=2.8.0
Requires-Dist: psutil>=5.9.5
Requires-Dist: py-cpuinfo>=9.0.0
Requires-Dist: pyyaml>=5.3.1
Requires-Dist: requests>=2.25.0
Requires-Dist: scapy>=2.5.0
Requires-Dist: seaborn>=0.12.0
Requires-Dist: tabulate>=0.9.0
Provides-Extra: dev
Requires-Dist: bandit>=1.7.0; extra == 'dev'
Requires-Dist: black>=23.0.0; extra == 'dev'
Requires-Dist: build>=1.2.1; extra == 'dev'
Requires-Dist: coverage[toml]>=7.0.0; extra == 'dev'
Requires-Dist: isort>=5.12.0; extra == 'dev'
Requires-Dist: mypy>=1.5.0; extra == 'dev'
Requires-Dist: pre-commit>=3.0.0; extra == 'dev'
Requires-Dist: pytest-cov>=4.0.0; extra == 'dev'
Requires-Dist: pytest-mock>=3.10.0; extra == 'dev'
Requires-Dist: pytest-xdist>=3.0.0; extra == 'dev'
Requires-Dist: pytest>=7.0.0; extra == 'dev'
Requires-Dist: ruff>=0.1.0; extra == 'dev'
Requires-Dist: safety>=2.0.0; extra == 'dev'
Requires-Dist: twine>=5.1.1; extra == 'dev'
Provides-Extra: docs
Requires-Dist: myst-parser>=2.0.0; extra == 'docs'
Requires-Dist: sphinx-autodoc-typehints>=1.24.0; extra == 'docs'
Requires-Dist: sphinx-rtd-theme>=1.3.0; extra == 'docs'
Requires-Dist: sphinx>=7.0.0; extra == 'docs'
